spec_augment.py
spec_augment-0.0.3.dist-info/LICENSE
spec_augment-0.0.3.dist-info/METADATA
spec_augment-0.0.3.dist-info/WHEEL
spec_augment-0.0.3.dist-info/top_level.txt
spec_augment-0.0.3.dist-info/RECORD
