Metadata-Version: 2.1
Name: spec-augment
Version: 0.0.3
Summary: Tensorflow Layer that implements the SpecAugment technique
Home-page: https://github.com/MichaelisTrofficus/spec_augment
Author: MTrofficus
Author-email: miguel.otero.pedrido.1993@gmail.com
License: UNKNOWN
Platform: UNKNOWN
Classifier: Programming Language :: Python :: 3
Classifier: License :: OSI Approved :: MIT License
Classifier: Operating System :: OS Independent
Requires-Python: >=3.5
License-File: LICENSE
Requires-Dist: tensorflow
